pulumi_cloudflare/__init__.py
pulumi_cloudflare/_inputs.py
pulumi_cloudflare/_utilities.py
pulumi_cloudflare/access_application.py
pulumi_cloudflare/access_ca_certificate.py
pulumi_cloudflare/access_custom_page.py
pulumi_cloudflare/access_group.py
pulumi_cloudflare/access_identity_provider.py
pulumi_cloudflare/access_keys_configuration.py
pulumi_cloudflare/access_mutual_tls_certificate.py
pulumi_cloudflare/access_mutual_tls_hostname_settings.py
pulumi_cloudflare/access_organization.py
pulumi_cloudflare/access_policy.py
pulumi_cloudflare/access_rule.py
pulumi_cloudflare/access_service_token.py
pulumi_cloudflare/access_tag.py
pulumi_cloudflare/account.py
pulumi_cloudflare/account_dns_settings.py
pulumi_cloudflare/account_dns_settings_internal_view.py
pulumi_cloudflare/account_member.py
pulumi_cloudflare/account_subscription.py
pulumi_cloudflare/account_token.py
pulumi_cloudflare/address_map.py
pulumi_cloudflare/api_shield.py
pulumi_cloudflare/api_shield_discovery_operation.py
pulumi_cloudflare/api_shield_operation.py
pulumi_cloudflare/api_shield_operation_schema_validation_settings.py
pulumi_cloudflare/api_shield_schema.py
pulumi_cloudflare/api_shield_schema_validation_settings.py
pulumi_cloudflare/api_token.py
pulumi_cloudflare/argo_smart_routing.py
pulumi_cloudflare/argo_tiered_caching.py
pulumi_cloudflare/authenticated_origin_pulls.py
pulumi_cloudflare/authenticated_origin_pulls_certificate.py
pulumi_cloudflare/authenticated_origin_pulls_settings.py
pulumi_cloudflare/bot_management.py
pulumi_cloudflare/byo_ip_prefix.py
pulumi_cloudflare/calls_sfu_app.py
pulumi_cloudflare/calls_turn_app.py
pulumi_cloudflare/certificate_pack.py
pulumi_cloudflare/cloud_connector_rules.py
pulumi_cloudflare/cloudforce_one_request.py
pulumi_cloudflare/cloudforce_one_request_asset.py
pulumi_cloudflare/cloudforce_one_request_message.py
pulumi_cloudflare/cloudforce_one_request_priority.py
pulumi_cloudflare/connectivity_directory_service.py
pulumi_cloudflare/content_scanning.py
pulumi_cloudflare-6.12.0.dist-info/METADATA
pulumi_cloudflare-6.12.0.dist-info/WHEEL
pulumi_cloudflare-6.12.0.dist-info/top_level.txt
pulumi_cloudflare-6.12.0.dist-info/RECORD
